csrd_utils/__init__.py
csrd_utils/config/__init__.py
csrd_utils/config/_config.py
csrd_utils/string_utils.py
csrd_utils-0.1.10.dist-info/METADATA
csrd_utils-0.1.10.dist-info/WHEEL
csrd_utils-0.1.10.dist-info/RECORD
